autotrain/__init__.py
autotrain/client.py
autotrain/commands.py
autotrain/config.py
autotrain/dataset.py
autotrain/help.py
autotrain/logging.py
autotrain/params.py
autotrain/parser.py
autotrain/project.py
autotrain/tasks.py
autotrain/utils.py
autotrain/app/__init__.py
autotrain/app/api_routes.py
autotrain/app/app.py
autotrain/app/colab.py
autotrain/app/db.py
autotrain/app/models.py
autotrain/app/oauth.py
autotrain/app/params.py
autotrain/app/training_api.py
autotrain/app/ui_routes.py
autotrain/app/utils.py
autotrain/app/static/logo.png
autotrain/app/static/scripts/fetch_data_and_update_models.js
autotrain/app/static/scripts/listeners.js
autotrain/app/static/scripts/logs.js
autotrain/app/static/scripts/poll.js
autotrain/app/static/scripts/utils.js
autotrain/app/templates/duplicate.html
autotrain/app/templates/error.html
autotrain/app/templates/index.html
autotrain/app/templates/login.html
autotrain/backends/__init__.py
autotrain/backends/base.py
autotrain/backends/endpoints.py
autotrain/backends/local.py
autotrain/backends/ngc.py
autotrain/backends/nvcf.py
autotrain/backends/spaces.py
autotrain/cli/__init__.py
autotrain/cli/autotrain.py
autotrain/cli/run_api.py
autotrain/cli/run_app.py
autotrain/cli/run_extractive_qa.py
autotrain/cli/run_image_classification.py
autotrain/cli/run_image_regression.py
autotrain/cli/run_llm.py
autotrain/cli/run_object_detection.py
autotrain/cli/run_sent_tranformers.py
autotrain/cli/run_seq2seq.py
autotrain/cli/run_setup.py
autotrain/cli/run_spacerunner.py
autotrain/cli/run_tabular.py
autotrain/cli/run_text_classification.py
autotrain/cli/run_text_regression.py
autotrain/cli/run_token_classification.py
autotrain/cli/run_tools.py
autotrain/cli/run_vlm.py
autotrain/cli/utils.py
autotrain/preprocessor/__init__.py
autotrain/preprocessor/tabular.py
autotrain/preprocessor/text.py
autotrain/preprocessor/vision.py
autotrain/preprocessor/vlm.py
autotrain/tools/__init__.py
autotrain/tools/convert_to_kohya.py
autotrain/tools/merge_adapter.py
autotrain_advanced-0.8.36.dist-info/LICENSE
autotrain_advanced-0.8.36.dist-info/METADATA
autotrain_advanced-0.8.36.dist-info/WHEEL
autotrain_advanced-0.8.36.dist-info/entry_points.txt
autotrain_advanced-0.8.36.dist-info/top_level.txt
autotrain_advanced-0.8.36.dist-info/RECORD
