Metadata-Version: 2.1
Name: autotrain-advanced
Version: 0.8.36
Home-page: https://github.com/huggingface/autotrain-advanced
Download-URL: https://github.com/huggingface/autotrain-advanced/tags
Author: HuggingFace Inc.
Author-email: autotrain@huggingface.co
License: Apache 2.0
Keywords: automl autonlp autotrain huggingface
Classifier: Development Status :: 5 - Production/Stable
Classifier: Intended Audience :: Developers
Classifier: Intended Audience :: Education
Classifier: Intended Audience :: Science/Research
Classifier: License :: OSI Approved :: Apache Software License
Classifier: Operating System :: OS Independent
Classifier: Programming Language :: Python :: 3.8
Classifier: Programming Language :: Python :: 3.9
Classifier: Programming Language :: Python :: 3.10
Classifier: Programming Language :: Python :: 3.11
Classifier: Topic :: Scientific/Engineering :: Artificial Intelligence
License-File: LICENSE
Requires-Dist: albumentations==1.4.23
Requires-Dist: datasets[vision]~=3.2.0
Requires-Dist: evaluate==0.4.3
Requires-Dist: ipadic==1.0.0
Requires-Dist: jiwer==3.0.5
Requires-Dist: joblib==1.4.2
Requires-Dist: loguru==0.7.3
Requires-Dist: pandas==2.2.3
Requires-Dist: nltk==3.9.1
Requires-Dist: optuna==4.1.0
Requires-Dist: Pillow==11.0.0
Requires-Dist: sacremoses==0.1.1
Requires-Dist: scikit-learn==1.6.0
Requires-Dist: sentencepiece==0.2.0
Requires-Dist: tqdm==4.67.1
Requires-Dist: werkzeug==3.1.3
Requires-Dist: xgboost==2.1.3
Requires-Dist: huggingface-hub==0.27.0
Requires-Dist: requests==2.32.3
Requires-Dist: einops==0.8.0
Requires-Dist: packaging==24.2
Requires-Dist: cryptography==44.0.0
Requires-Dist: nvitop==1.3.2
Requires-Dist: tensorboard==2.18.0
Requires-Dist: peft==0.14.0
Requires-Dist: trl==0.13.0
Requires-Dist: tiktoken==0.8.0
Requires-Dist: transformers==4.48.0
Requires-Dist: accelerate==1.2.1
Requires-Dist: rouge-score==0.1.2
Requires-Dist: py7zr==0.22.0
Requires-Dist: fastapi==0.115.6
Requires-Dist: uvicorn==0.34.0
Requires-Dist: python-multipart==0.0.20
Requires-Dist: pydantic==2.10.4
Requires-Dist: hf-transfer
Requires-Dist: pyngrok==7.2.1
Requires-Dist: authlib==1.4.0
Requires-Dist: itsdangerous==2.2.0
Requires-Dist: seqeval==1.2.2
Requires-Dist: httpx==0.28.1
Requires-Dist: pyyaml==6.0.2
Requires-Dist: timm==1.0.12
Requires-Dist: torchmetrics==1.6.0
Requires-Dist: pycocotools==2.0.8
Requires-Dist: sentence-transformers==3.3.1
Requires-Dist: bitsandbytes==0.45.0; sys_platform == "linux"
Provides-Extra: base
Requires-Dist: albumentations==1.4.23; extra == "base"
Requires-Dist: datasets[vision]~=3.2.0; extra == "base"
Requires-Dist: evaluate==0.4.3; extra == "base"
Requires-Dist: ipadic==1.0.0; extra == "base"
Requires-Dist: jiwer==3.0.5; extra == "base"
Requires-Dist: joblib==1.4.2; extra == "base"
Requires-Dist: loguru==0.7.3; extra == "base"
Requires-Dist: pandas==2.2.3; extra == "base"
Requires-Dist: nltk==3.9.1; extra == "base"
Requires-Dist: optuna==4.1.0; extra == "base"
Requires-Dist: Pillow==11.0.0; extra == "base"
Requires-Dist: sacremoses==0.1.1; extra == "base"
Requires-Dist: scikit-learn==1.6.0; extra == "base"
Requires-Dist: sentencepiece==0.2.0; extra == "base"
Requires-Dist: tqdm==4.67.1; extra == "base"
Requires-Dist: werkzeug==3.1.3; extra == "base"
Requires-Dist: xgboost==2.1.3; extra == "base"
Requires-Dist: huggingface-hub==0.27.0; extra == "base"
Requires-Dist: requests==2.32.3; extra == "base"
Requires-Dist: einops==0.8.0; extra == "base"
Requires-Dist: packaging==24.2; extra == "base"
Requires-Dist: cryptography==44.0.0; extra == "base"
Requires-Dist: nvitop==1.3.2; extra == "base"
Requires-Dist: tensorboard==2.18.0; extra == "base"
Requires-Dist: peft==0.14.0; extra == "base"
Requires-Dist: trl==0.13.0; extra == "base"
Requires-Dist: tiktoken==0.8.0; extra == "base"
Requires-Dist: transformers==4.48.0; extra == "base"
Requires-Dist: accelerate==1.2.1; extra == "base"
Requires-Dist: rouge-score==0.1.2; extra == "base"
Requires-Dist: py7zr==0.22.0; extra == "base"
Requires-Dist: fastapi==0.115.6; extra == "base"
Requires-Dist: uvicorn==0.34.0; extra == "base"
Requires-Dist: python-multipart==0.0.20; extra == "base"
Requires-Dist: pydantic==2.10.4; extra == "base"
Requires-Dist: hf-transfer; extra == "base"
Requires-Dist: pyngrok==7.2.1; extra == "base"
Requires-Dist: authlib==1.4.0; extra == "base"
Requires-Dist: itsdangerous==2.2.0; extra == "base"
Requires-Dist: seqeval==1.2.2; extra == "base"
Requires-Dist: httpx==0.28.1; extra == "base"
Requires-Dist: pyyaml==6.0.2; extra == "base"
Requires-Dist: timm==1.0.12; extra == "base"
Requires-Dist: torchmetrics==1.6.0; extra == "base"
Requires-Dist: pycocotools==2.0.8; extra == "base"
Requires-Dist: sentence-transformers==3.3.1; extra == "base"
Requires-Dist: bitsandbytes==0.45.0; sys_platform == "linux" and extra == "base"
Provides-Extra: client
Requires-Dist: requests; extra == "client"
Requires-Dist: loguru; extra == "client"
Provides-Extra: dev
Requires-Dist: albumentations==1.4.23; extra == "dev"
Requires-Dist: datasets[vision]~=3.2.0; extra == "dev"
Requires-Dist: evaluate==0.4.3; extra == "dev"
Requires-Dist: ipadic==1.0.0; extra == "dev"
Requires-Dist: jiwer==3.0.5; extra == "dev"
Requires-Dist: joblib==1.4.2; extra == "dev"
Requires-Dist: loguru==0.7.3; extra == "dev"
Requires-Dist: pandas==2.2.3; extra == "dev"
Requires-Dist: nltk==3.9.1; extra == "dev"
Requires-Dist: optuna==4.1.0; extra == "dev"
Requires-Dist: Pillow==11.0.0; extra == "dev"
Requires-Dist: sacremoses==0.1.1; extra == "dev"
Requires-Dist: scikit-learn==1.6.0; extra == "dev"
Requires-Dist: sentencepiece==0.2.0; extra == "dev"
Requires-Dist: tqdm==4.67.1; extra == "dev"
Requires-Dist: werkzeug==3.1.3; extra == "dev"
Requires-Dist: xgboost==2.1.3; extra == "dev"
Requires-Dist: huggingface-hub==0.27.0; extra == "dev"
Requires-Dist: requests==2.32.3; extra == "dev"
Requires-Dist: einops==0.8.0; extra == "dev"
Requires-Dist: packaging==24.2; extra == "dev"
Requires-Dist: cryptography==44.0.0; extra == "dev"
Requires-Dist: nvitop==1.3.2; extra == "dev"
Requires-Dist: tensorboard==2.18.0; extra == "dev"
Requires-Dist: peft==0.14.0; extra == "dev"
Requires-Dist: trl==0.13.0; extra == "dev"
Requires-Dist: tiktoken==0.8.0; extra == "dev"
Requires-Dist: transformers==4.48.0; extra == "dev"
Requires-Dist: accelerate==1.2.1; extra == "dev"
Requires-Dist: rouge-score==0.1.2; extra == "dev"
Requires-Dist: py7zr==0.22.0; extra == "dev"
Requires-Dist: fastapi==0.115.6; extra == "dev"
Requires-Dist: uvicorn==0.34.0; extra == "dev"
Requires-Dist: python-multipart==0.0.20; extra == "dev"
Requires-Dist: pydantic==2.10.4; extra == "dev"
Requires-Dist: hf-transfer; extra == "dev"
Requires-Dist: pyngrok==7.2.1; extra == "dev"
Requires-Dist: authlib==1.4.0; extra == "dev"
Requires-Dist: itsdangerous==2.2.0; extra == "dev"
Requires-Dist: seqeval==1.2.2; extra == "dev"
Requires-Dist: httpx==0.28.1; extra == "dev"
Requires-Dist: pyyaml==6.0.2; extra == "dev"
Requires-Dist: timm==1.0.12; extra == "dev"
Requires-Dist: torchmetrics==1.6.0; extra == "dev"
Requires-Dist: pycocotools==2.0.8; extra == "dev"
Requires-Dist: sentence-transformers==3.3.1; extra == "dev"
Requires-Dist: black; extra == "dev"
Requires-Dist: isort; extra == "dev"
Requires-Dist: flake8==3.7.9; extra == "dev"
Requires-Dist: pytest; extra == "dev"
Requires-Dist: bitsandbytes==0.45.0; sys_platform == "linux" and extra == "dev"
Provides-Extra: docs
Requires-Dist: albumentations==1.4.23; extra == "docs"
Requires-Dist: datasets[vision]~=3.2.0; extra == "docs"
Requires-Dist: evaluate==0.4.3; extra == "docs"
Requires-Dist: ipadic==1.0.0; extra == "docs"
Requires-Dist: jiwer==3.0.5; extra == "docs"
Requires-Dist: joblib==1.4.2; extra == "docs"
Requires-Dist: loguru==0.7.3; extra == "docs"
Requires-Dist: pandas==2.2.3; extra == "docs"
Requires-Dist: nltk==3.9.1; extra == "docs"
Requires-Dist: optuna==4.1.0; extra == "docs"
Requires-Dist: Pillow==11.0.0; extra == "docs"
Requires-Dist: sacremoses==0.1.1; extra == "docs"
Requires-Dist: scikit-learn==1.6.0; extra == "docs"
Requires-Dist: sentencepiece==0.2.0; extra == "docs"
Requires-Dist: tqdm==4.67.1; extra == "docs"
Requires-Dist: werkzeug==3.1.3; extra == "docs"
Requires-Dist: xgboost==2.1.3; extra == "docs"
Requires-Dist: huggingface-hub==0.27.0; extra == "docs"
Requires-Dist: requests==2.32.3; extra == "docs"
Requires-Dist: einops==0.8.0; extra == "docs"
Requires-Dist: packaging==24.2; extra == "docs"
Requires-Dist: cryptography==44.0.0; extra == "docs"
Requires-Dist: nvitop==1.3.2; extra == "docs"
Requires-Dist: tensorboard==2.18.0; extra == "docs"
Requires-Dist: peft==0.14.0; extra == "docs"
Requires-Dist: trl==0.13.0; extra == "docs"
Requires-Dist: tiktoken==0.8.0; extra == "docs"
Requires-Dist: transformers==4.48.0; extra == "docs"
Requires-Dist: accelerate==1.2.1; extra == "docs"
Requires-Dist: rouge-score==0.1.2; extra == "docs"
Requires-Dist: py7zr==0.22.0; extra == "docs"
Requires-Dist: fastapi==0.115.6; extra == "docs"
Requires-Dist: uvicorn==0.34.0; extra == "docs"
Requires-Dist: python-multipart==0.0.20; extra == "docs"
Requires-Dist: pydantic==2.10.4; extra == "docs"
Requires-Dist: hf-transfer; extra == "docs"
Requires-Dist: pyngrok==7.2.1; extra == "docs"
Requires-Dist: authlib==1.4.0; extra == "docs"
Requires-Dist: itsdangerous==2.2.0; extra == "docs"
Requires-Dist: seqeval==1.2.2; extra == "docs"
Requires-Dist: httpx==0.28.1; extra == "docs"
Requires-Dist: pyyaml==6.0.2; extra == "docs"
Requires-Dist: timm==1.0.12; extra == "docs"
Requires-Dist: torchmetrics==1.6.0; extra == "docs"
Requires-Dist: pycocotools==2.0.8; extra == "docs"
Requires-Dist: sentence-transformers==3.3.1; extra == "docs"
Requires-Dist: recommonmark; extra == "docs"
Requires-Dist: sphinx==3.1.2; extra == "docs"
Requires-Dist: sphinx-markdown-tables; extra == "docs"
Requires-Dist: sphinx-rtd-theme==0.4.3; extra == "docs"
Requires-Dist: sphinx-copybutton; extra == "docs"
Requires-Dist: bitsandbytes==0.45.0; sys_platform == "linux" and extra == "docs"
Provides-Extra: quality
Requires-Dist: albumentations==1.4.23; extra == "quality"
Requires-Dist: datasets[vision]~=3.2.0; extra == "quality"
Requires-Dist: evaluate==0.4.3; extra == "quality"
Requires-Dist: ipadic==1.0.0; extra == "quality"
Requires-Dist: jiwer==3.0.5; extra == "quality"
Requires-Dist: joblib==1.4.2; extra == "quality"
Requires-Dist: loguru==0.7.3; extra == "quality"
Requires-Dist: pandas==2.2.3; extra == "quality"
Requires-Dist: nltk==3.9.1; extra == "quality"
Requires-Dist: optuna==4.1.0; extra == "quality"
Requires-Dist: Pillow==11.0.0; extra == "quality"
Requires-Dist: sacremoses==0.1.1; extra == "quality"
Requires-Dist: scikit-learn==1.6.0; extra == "quality"
Requires-Dist: sentencepiece==0.2.0; extra == "quality"
Requires-Dist: tqdm==4.67.1; extra == "quality"
Requires-Dist: werkzeug==3.1.3; extra == "quality"
Requires-Dist: xgboost==2.1.3; extra == "quality"
Requires-Dist: huggingface-hub==0.27.0; extra == "quality"
Requires-Dist: requests==2.32.3; extra == "quality"
Requires-Dist: einops==0.8.0; extra == "quality"
Requires-Dist: packaging==24.2; extra == "quality"
Requires-Dist: cryptography==44.0.0; extra == "quality"
Requires-Dist: nvitop==1.3.2; extra == "quality"
Requires-Dist: tensorboard==2.18.0; extra == "quality"
Requires-Dist: peft==0.14.0; extra == "quality"
Requires-Dist: trl==0.13.0; extra == "quality"
Requires-Dist: tiktoken==0.8.0; extra == "quality"
Requires-Dist: transformers==4.48.0; extra == "quality"
Requires-Dist: accelerate==1.2.1; extra == "quality"
Requires-Dist: rouge-score==0.1.2; extra == "quality"
Requires-Dist: py7zr==0.22.0; extra == "quality"
Requires-Dist: fastapi==0.115.6; extra == "quality"
Requires-Dist: uvicorn==0.34.0; extra == "quality"
Requires-Dist: python-multipart==0.0.20; extra == "quality"
Requires-Dist: pydantic==2.10.4; extra == "quality"
Requires-Dist: hf-transfer; extra == "quality"
Requires-Dist: pyngrok==7.2.1; extra == "quality"
Requires-Dist: authlib==1.4.0; extra == "quality"
Requires-Dist: itsdangerous==2.2.0; extra == "quality"
Requires-Dist: seqeval==1.2.2; extra == "quality"
Requires-Dist: httpx==0.28.1; extra == "quality"
Requires-Dist: pyyaml==6.0.2; extra == "quality"
Requires-Dist: timm==1.0.12; extra == "quality"
Requires-Dist: torchmetrics==1.6.0; extra == "quality"
Requires-Dist: pycocotools==2.0.8; extra == "quality"
Requires-Dist: sentence-transformers==3.3.1; extra == "quality"
Requires-Dist: black; extra == "quality"
Requires-Dist: isort; extra == "quality"
Requires-Dist: flake8==3.7.9; extra == "quality"
Requires-Dist: bitsandbytes==0.45.0; sys_platform == "linux" and extra == "quality"
